asposewordscloud/__init__.py
asposewordscloud/api_client.py
asposewordscloud/configuration.py
asposewordscloud/rest.py
asposewordscloud/apis/__init__.py
asposewordscloud/apis/words_api.py
asposewordscloud/models/__init__.py
asposewordscloud/models/api_error.py
asposewordscloud/models/available_fonts_response.py
asposewordscloud/models/azw3_save_options_data.py
asposewordscloud/models/bmp_save_options_data.py
asposewordscloud/models/bookmark.py
asposewordscloud/models/bookmark_data.py
asposewordscloud/models/bookmark_insert.py
asposewordscloud/models/bookmark_response.py
asposewordscloud/models/bookmarks.py
asposewordscloud/models/bookmarks_outline_level_data.py
asposewordscloud/models/bookmarks_response.py
asposewordscloud/models/border.py
asposewordscloud/models/border_response.py
asposewordscloud/models/borders_collection.py
asposewordscloud/models/borders_response.py
asposewordscloud/models/comment.py
asposewordscloud/models/comment_insert.py
asposewordscloud/models/comment_link.py
asposewordscloud/models/comment_range_end.py
asposewordscloud/models/comment_range_start.py
asposewordscloud/models/comment_response.py
asposewordscloud/models/comment_update.py
asposewordscloud/models/comments_collection.py
asposewordscloud/models/comments_response.py
asposewordscloud/models/compare_data.py
asposewordscloud/models/compare_options.py
asposewordscloud/models/compress_options.py
asposewordscloud/models/compress_response.py
asposewordscloud/models/csv_data_load_options.py
asposewordscloud/models/custom_xml_part.py
asposewordscloud/models/custom_xml_part_insert.py
asposewordscloud/models/custom_xml_part_link.py
asposewordscloud/models/custom_xml_part_response.py
asposewordscloud/models/custom_xml_part_update.py
asposewordscloud/models/custom_xml_parts_collection.py
asposewordscloud/models/custom_xml_parts_response.py
asposewordscloud/models/digital_signature_details.py
asposewordscloud/models/doc_save_options_data.py
asposewordscloud/models/docm_save_options_data.py
aspose_words_cloud-25.12.0.dist-info/LICENSE
aspose_words_cloud-25.12.0.dist-info/METADATA
aspose_words_cloud-25.12.0.dist-info/WHEEL
aspose_words_cloud-25.12.0.dist-info/top_level.txt
aspose_words_cloud-25.12.0.dist-info/RECORD
