Metadata-Version: 2.1
Name: aspose-words-cloud
Version: 25.12.0
Summary: Python Cloud SDK wraps Aspose.Words Cloud API so you could seamlessly integrate Microsoft Word file generation, manipulation, conversion & inspection features into your own python applications.
Home-page: https://github.com/aspose-words-cloud/aspose-words-cloud-python
Author: Aspose
Author-email: aspose.cloud@aspose.com
License: UNKNOWN
Keywords: office,convert,word,pdf,docx,html,rtf,png,jpg,split,merge,edit,word to pdf,pdf to word,docx to pdf,pdf to docx,word to html,html to word,reporting,mailmerge,statistics,watermark,fields,generate,create,report,table,paragraph,images,text,generator,creator,maker
Platform: UNKNOWN
Classifier: Development Status :: 5 - Production/Stable
Classifier: Intended Audience :: Developers
Classifier: Topic :: Office/Business :: Office Suites
Classifier: Topic :: Software Development :: Libraries
Classifier: License :: OSI Approved :: MIT License
Classifier: Programming Language :: Python :: 3.8
Classifier: Programming Language :: Python :: 3.9
Classifier: Programming Language :: Python :: 3.10
Classifier: Programming Language :: Python :: 3.11
Classifier: Programming Language :: Python :: 3.12
Classifier: Programming Language :: Python :: 3.13
License-File: LICENSE
Requires-Dist: urllib3 (>=1.16)
Requires-Dist: six (>=1.10)
Requires-Dist: requests-toolbelt (>=0.9.1)
Requires-Dist: certifi
Requires-Dist: python-dateutil
